epicchain/__init__.py
epicchain/py.typed
epicchain/settings.py
epicchain/singleton.py
epicchain/vm.py
epicchain/api/__init__.py
epicchain/api/noderpc.py
epicchain/api/wrappers.py
epicchain/api/helpers/__init__.py
epicchain/api/helpers/essentiallib.py
epicchain/api/helpers/signing.py
epicchain/api/helpers/txbuilder.py
epicchain/api/helpers/unwrap.py
epicchain/contracts/__init__.py
epicchain/contracts/abi.py
epicchain/contracts/callflags.py
epicchain/contracts/contract.py
epicchain/contracts/findoptions.py
epicchain/contracts/manifest.py
epicchain/contracts/utils.py
epicchain/contracts/xef.py
epicchain/core/__init__.py
epicchain/core/interfaces.py
epicchain/core/serialization.py
epicchain/core/utils.py
epicchain/core/cryptography/__init__.py
epicchain/core/cryptography/bloomfilter.py
epicchain/core/cryptography/ecc.py
epicchain/core/cryptography/merkletree.py
epicchain/core/types/__init__.py
epicchain/core/types/uint.py
epicchain/network/__init__.py
epicchain/network/capabilities.py
epicchain/network/ipfilter.py
epicchain/network/message.py
epicchain/network/node.py
epicchain/network/relaycache.py
epicchain/network/convenience/__init__.py
epicchain/network/convenience/flightinfo.py
epicchain/network/convenience/nodemanager.py
epicchain/network/convenience/nodeweight.py
epicchain/network/convenience/requestinfo.py
epicchain/network/convenience/syncmanager.py
epicchain/network/payloads/__init__.py
epicchain/network/payloads/address.py
epicchain/network/payloads/block.py
epicchain/network/payloads/consensus.py
epicchain/network/payloads/empty.py
epicchain/network/payloads/extensible.py
epicchain/network/payloads/filter.py
epicchain/network/payloads/inventory.py
epicchain/network/payloads/ping.py
epicchain/network/payloads/transaction.py
epicchain/network/payloads/verification.py
epicchain/network/payloads/version.py
epicchain/wallet/__init__.py
epicchain/wallet/account.py
epicchain/wallet/scrypt_parameters.py
epicchain/wallet/types.py
epicchain/wallet/utils.py
epicchain_python_sdk-1.0.0.dist-info/licenses/LICENSE.md
epicchain_python_sdk-1.0.0.dist-info/METADATA
epicchain_python_sdk-1.0.0.dist-info/WHEEL
epicchain_python_sdk-1.0.0.dist-info/top_level.txt
epicchain_python_sdk-1.0.0.dist-info/RECORD
