Metadata-Version: 2.4
Name: epicchain-python-sdk
Version: 1.0.0
Summary: Python SDK for the EpicChain blockchain
Author-email: xmoohad <xmoohad@epic-chain.org>
Maintainer-email: xmoohad <xmoohad@epic-chain.org>
License: Copyright (c) 2025 EpicChain Labs
Project-URL: repository, https://github.com/epicchainlabs/Python-SDK-for-the-EpicChain-blockchain
Keywords: EpicChain,Blockchain,SDK
Requires-Python: <=3.13,>=3.11.0
License-File: LICENSE.md
Requires-Dist: aiodns==3.1.1
Requires-Dist: aiohttp==3.9.3
Requires-Dist: base58==2.1.1
Requires-Dist: bitarray==2.8.5
Requires-Dist: Events==0.5
Requires-Dist: jsonschema>=4.19.0
Requires-Dist: lz4==4.3.2
Requires-Dist: epicchaincrypto==0.4.3
Requires-Dist: netaddr>=0.9.0
Requires-Dist: orjson>=3.9.10
Requires-Dist: pycryptodome==3.19.0
Requires-Dist: pybiginteger==1.3.3
Requires-Dist: pybiginteger-stubs==1.3.3
Provides-Extra: dev
Requires-Dist: aioresponses==0.7.6; extra == "dev"
Requires-Dist: black==23.9.1; extra == "dev"
Requires-Dist: build==0.10.0; extra == "dev"
Requires-Dist: bump-my-version==0.12.0; extra == "dev"
Requires-Dist: coverage>=7.3.2; extra == "dev"
Requires-Dist: docutils==0.17.1; extra == "dev"
Requires-Dist: mypy==1.7.1; extra == "dev"
Requires-Dist: mypy-extensions==1.0.0; extra == "dev"
Provides-Extra: docs
Requires-Dist: mkdocs==1.4.1; extra == "docs"
Requires-Dist: mkdocs-material==8.5.7; extra == "docs"
Requires-Dist: mkdocs-material-extensions==1.1; extra == "docs"
Requires-Dist: mkapi-fix-coz==0.1.0; extra == "docs"
Dynamic: license-file
